{
  "block": {
    "signature": {
      "name": "",
      "description": "",
      "extra_description": "",
      "search_terms": [],
      "required_positional": [],
      "optional_positional": [],
      "rest_positional": null,
      "named": [],
      "input_output_types": [],
      "allow_variants_without_examples": false,
      "is_filter": false,
      "creates_scope": false,
      "allows_unknown_args": false,
      "complete": null,
      "category": "Default"
    },
    "pipelines": [
      {
        "elements": [
          {
            "pipe": null,
            "expr": {
              "expr": {
                "FullCellPath": {
                  "head": {
                    "expr": {
                      "List": [
                        {
                          "Item": {
                            "expr": {
                              "String": "nu_plugin_inc"
                            },
                            "span": {
                              "start": 148941,
                              "end": 148954
                            },
                            "span_id": 40099,
                            "ty": "String"
                          }
                        },
                        {
                          "Item": {
                            "expr": {
                              "String": "nu_plugin_polars"
                            },
                            "span": {
                              "start": 148957,
                              "end": 148973
                            },
                            "span_id": 40109,
                            "ty": "String"
                          }
                        },
                        {
                          "Item": {
                            "expr": {
                              "String": "nu_plugin_gstat"
                            },
                            "span": {
                              "start": 148976,
                              "end": 148991
                            },
                            "span_id": 40119,
                            "ty": "String"
                          }
                        },
                        {
                          "Item": {
                            "expr": {
                              "String": "nu_plugin_formats"
                            },
                            "span": {
                              "start": 148994,
                              "end": 149011
                            },
                            "span_id": 40129,
                            "ty": "String"
                          }
                        },
                        {
                          "Item": {
                            "expr": {
                              "String": "nu_plugin_query"
                            },
                            "span": {
                              "start": 149014,
                              "end": 149029
                            },
                            "span_id": 40139,
                            "ty": "String"
                          }
                        }
                      ]
                    },
                    "span": {
                      "start": 148939,
                      "end": 149031
                    },
                    "span_id": 40140,
                    "ty": {
                      "List": "String"
                    }
                  },
                  "tail": []
                }
              },
              "span": {
                "start": 148939,
                "end": 149031
              },
              "span_id": 40141,
              "ty": {
                "List": "String"
              }
            },
            "redirection": null
          },
          {
            "pipe": {
              "start": 149032,
              "end": 149033
            },
            "expr": {
              "expr": {
                "Call": {
                  "decl_id": 76,
                  "head": {
                    "start": 149034,
                    "end": 149038
                  },
                  "arguments": [
                    {
                      "Positional": {
                        "expr": {
                          "Closure": 1710
                        },
                        "span": {
                          "start": 149039,
                          "end": 149069
                        },
                        "span_id": 40172,
                        "ty": "Closure"
                      }
                    }
                  ],
                  "parser_info": {}
                }
              },
              "span": {
                "start": 149034,
                "end": 149069
              },
              "span_id": 40173,
              "ty": "Any"
            },
            "redirection": null
          },
          {
            "pipe": {
              "start": 149070,
              "end": 149071
            },
            "expr": {
              "expr": {
                "Call": {
                  "decl_id": 31,
                  "head": {
                    "start": 149072,
                    "end": 149078
                  },
                  "arguments": [],
                  "parser_info": {}
                }
              },
              "span": {
                "start": 149072,
                "end": 149078
              },
              "span_id": 40182,
              "ty": "Nothing"
            },
            "redirection": null
          }
        ]
      }
    ],
    "captures": [],
    "redirect_env": false,
    "ir_block": {
      "instructions": [
        {
          "LoadLiteral": {
            "dst": 0,
            "lit": {
              "List": {
                "capacity": 5
              }
            }
          }
        },
        {
          "LoadLiteral": {
            "dst": 1,
            "lit": {
              "String": {
                "start": 0,
                "len": 13
              }
            }
          }
        },
        {
          "ListPush": {
            "src_dst": 0,
            "item": 1
          }
        },
        {
          "LoadLiteral": {
            "dst": 1,
            "lit": {
              "String": {
                "start": 13,
                "len": 16
              }
            }
          }
        },
        {
          "ListPush": {
            "src_dst": 0,
            "item": 1
          }
        },
        {
          "LoadLiteral": {
            "dst": 1,
            "lit": {
              "String": {
                "start": 29,
                "len": 15
              }
            }
          }
        },
        {
          "ListPush": {
            "src_dst": 0,
            "item": 1
          }
        },
        {
          "LoadLiteral": {
            "dst": 1,
            "lit": {
              "String": {
                "start": 44,
                "len": 17
              }
            }
          }
        },
        {
          "ListPush": {
            "src_dst": 0,
            "item": 1
          }
        },
        {
          "LoadLiteral": {
            "dst": 1,
            "lit": {
              "String": {
                "start": 61,
                "len": 15
              }
            }
          }
        },
        {
          "ListPush": {
            "src_dst": 0,
            "item": 1
          }
        },
        {
          "LoadLiteral": {
            "dst": 1,
            "lit": {
              "Closure": 1710
            }
          }
        },
        {
          "PushPositional": {
            "src": 1
          }
        },
        {
          "RedirectOut": {
            "mode": "Null"
          }
        },
        {
          "Call": {
            "decl_id": 76,
            "src_dst": 0
          }
        },
        {
          "RedirectOut": {
            "mode": "Caller"
          }
        },
        {
          "RedirectErr": {
            "mode": "Caller"
          }
        },
        {
          "Call": {
            "decl_id": 31,
            "src_dst": 0
          }
        },
        {
          "Return": {
            "src": 0
          }
        }
      ],
      "spans": [
        {
          "start": 148939,
          "end": 149031
        },
        {
          "start": 148941,
          "end": 148954
        },
        {
          "start": 148941,
          "end": 148954
        },
        {
          "start": 148957,
          "end": 148973
        },
        {
          "start": 148957,
          "end": 148973
        },
        {
          "start": 148976,
          "end": 148991
        },
        {
          "start": 148976,
          "end": 148991
        },
        {
          "start": 148994,
          "end": 149011
        },
        {
          "start": 148994,
          "end": 149011
        },
        {
          "start": 149014,
          "end": 149029
        },
        {
          "start": 149014,
          "end": 149029
        },
        {
          "start": 149039,
          "end": 149069
        },
        {
          "start": 149039,
          "end": 149069
        },
        {
          "start": 149032,
          "end": 149033
        },
        {
          "start": 149034,
          "end": 149038
        },
        {
          "start": 148939,
          "end": 149078
        },
        {
          "start": 148939,
          "end": 149078
        },
        {
          "start": 149072,
          "end": 149078
        },
        {
          "start": 148939,
          "end": 149078
        }
      ],
      "data": [
        110,
        117,
        95,
        112,
        108,
        117,
        103,
        105,
        110,
        95,
        105,
        110,
        99,
        110,
        117,
        95,
        112,
        108,
        117,
        103,
        105,
        110,
        95,
        112,
        111,
        108,
        97,
        114,
        115,
        110,
        117,
        95,
        112,
        108,
        117,
        103,
        105,
        110,
        95,
        103,
        115,
        116,
        97,
        116,
        110,
        117,
        95,
        112,
        108,
        117,
        103,
        105,
        110,
        95,
        102,
        111,
        114,
        109,
        97,
        116,
        115,
        110,
        117,
        95,
        112,
        108,
        117,
        103,
        105,
        110,
        95,
        113,
        117,
        101,
        114,
        121
      ],
      "ast": [
        null,
        null,
        null,
        null,
        null,
        null,
        null,
        null,
        null,
        null,
        null,
        null,
        null,
        null,
        null,
        null,
        null,
        null,
        null
      ],
      "comments": [
        "",
        "",
        "",
        "",
        "",
        "",
        "",
        "",
        "",
        "",
        "",
        "",
        "",
        "",
        "",
        "",
        "",
        "",
        ""
      ],
      "register_count": 2,
      "file_count": 0
    },
    "span": {
      "start": 148939,
      "end": 149078
    }
  },
  "error": null
}
